zenodo_accessrequests/__init__.py
zenodo_accessrequests/admin.py
zenodo_accessrequests/config.py
zenodo_accessrequests/errors.py
zenodo_accessrequests/ext.py
zenodo_accessrequests/forms.py
zenodo_accessrequests/helpers.py
zenodo_accessrequests/models.py
zenodo_accessrequests/proxies.py
zenodo_accessrequests/receivers.py
zenodo_accessrequests/signals.py
zenodo_accessrequests/tokens.py
zenodo_accessrequests/utils.py
zenodo_accessrequests/version.py
zenodo_accessrequests/widgets.py
zenodo_accessrequests/templates/zenodo_accessrequests/_macro.html
zenodo_accessrequests/templates/zenodo_accessrequests/_pagination.html
zenodo_accessrequests/templates/zenodo_accessrequests/access_request.html
zenodo_accessrequests/templates/zenodo_accessrequests/base.html
zenodo_accessrequests/templates/zenodo_accessrequests/index.html
zenodo_accessrequests/templates/zenodo_accessrequests/link_description.tpl
zenodo_accessrequests/templates/zenodo_accessrequests/emails/accepted.tpl
zenodo_accessrequests/templates/zenodo_accessrequests/emails/confirmation.tpl
zenodo_accessrequests/templates/zenodo_accessrequests/emails/new_request.tpl
zenodo_accessrequests/templates/zenodo_accessrequests/emails/rejected.tpl
zenodo_accessrequests/templates/zenodo_accessrequests/emails/validate_email.tpl
zenodo_accessrequests/templates/zenodo_accessrequests/settings/base.html
zenodo_accessrequests/templates/zenodo_accessrequests/settings/index.html
zenodo_accessrequests/templates/zenodo_accessrequests/settings/request.html
zenodo_accessrequests/views/__init__.py
zenodo_accessrequests/views/requests.py
zenodo_accessrequests/views/settings.py
zenodo_accessrequests-1.0.0a5.dist-info/AUTHORS.rst
zenodo_accessrequests-1.0.0a5.dist-info/LICENSE
zenodo_accessrequests-1.0.0a5.dist-info/METADATA
zenodo_accessrequests-1.0.0a5.dist-info/WHEEL
zenodo_accessrequests-1.0.0a5.dist-info/entry_points.txt
zenodo_accessrequests-1.0.0a5.dist-info/top_level.txt
zenodo_accessrequests-1.0.0a5.dist-info/RECORD
