Metadata-Version: 2.1
Name: zenodo-accessrequests
Version: 1.0.0a5
Summary: Zenodo module for providing access request feature.
Home-page: https://github.com/zenodo/zenodo-accessrequests
Author: CERN
Author-email: info@zenodo.org
License: GPLv2
Keywords: invenio TODO
Platform: any
Classifier: Environment :: Web Environment
Classifier: Intended Audience :: Developers
Classifier: License :: OSI Approved :: GNU General Public License v2 (GPLv2)
Classifier: Operating System :: OS Independent
Classifier: Programming Language :: Python
Classifier: Topic :: Internet :: WWW/HTTP :: Dynamic Content
Classifier: Topic :: Software Development :: Libraries :: Python Modules
Classifier: Programming Language :: Python :: 2
Classifier: Programming Language :: Python :: 2.7
Classifier: Programming Language :: Python :: 3
Classifier: Programming Language :: Python :: 3.5
Classifier: Development Status :: 3 - Alpha
Requires-Dist: blinker (>=1.4)
Requires-Dist: Flask-BabelEx (>=0.9.2)
Requires-Dist: Flask-Breadcrumbs (>=0.4.0)
Requires-Dist: Flask (>=1.0.2)
Requires-Dist: invenio-access (>=1.0.0a11)
Requires-Dist: invenio-accounts (>=1.0.0b1)
Requires-Dist: invenio-db (>=1.0.0b3)
Requires-Dist: invenio-files-rest (>=1.0.0a14)
Requires-Dist: invenio-formatter (>=1.0.0a2)
Requires-Dist: invenio-i18n (>=1.0.0b1)
Requires-Dist: invenio-mail (>=1.0.0a5)
Requires-Dist: invenio-pidstore (>=1.0.0b1)
Requires-Dist: invenio-records (>=1.0.0b1)
Requires-Dist: itsdangerous (>=1.1.0)
Requires-Dist: WTForms (>=2.0)
Provides-Extra: all
Requires-Dist: Sphinx (<1.6,>=1.5) ; extra == 'all'
Requires-Dist: check-manifest (>=0.35) ; extra == 'all'
Requires-Dist: coverage (>=4.0) ; extra == 'all'
Requires-Dist: invenio-records-ui (>=1.0.1) ; extra == 'all'
Requires-Dist: isort (>=4.3.4) ; extra == 'all'
Requires-Dist: mock (>=1.3.0) ; extra == 'all'
Requires-Dist: pydocstyle (>=2.0.0) ; extra == 'all'
Requires-Dist: pytest-cache (>=1.0) ; extra == 'all'
Requires-Dist: pytest-cov (>=2.5.1) ; extra == 'all'
Requires-Dist: pytest-pep8 (>=1.0.6) ; extra == 'all'
Requires-Dist: pytest (>=3.7.0) ; extra == 'all'
Provides-Extra: docs
Requires-Dist: Sphinx (<1.6,>=1.5) ; extra == 'docs'
Provides-Extra: tests
Requires-Dist: check-manifest (>=0.35) ; extra == 'tests'
Requires-Dist: coverage (>=4.0) ; extra == 'tests'
Requires-Dist: invenio-records-ui (>=1.0.1) ; extra == 'tests'
Requires-Dist: isort (>=4.3.4) ; extra == 'tests'
Requires-Dist: mock (>=1.3.0) ; extra == 'tests'
Requires-Dist: pydocstyle (>=2.0.0) ; extra == 'tests'
Requires-Dist: pytest-cache (>=1.0) ; extra == 'tests'
Requires-Dist: pytest-cov (>=2.5.1) ; extra == 'tests'
Requires-Dist: pytest-pep8 (>=1.0.6) ; extra == 'tests'
Requires-Dist: pytest (>=3.7.0) ; extra == 'tests'
